{
    "kind": "youtube#videoListResponse",
    "etag": "Ea9bUkfKjfKKb1TpYxUMIGE8qjE",
    "items": [
        {
            "kind": "youtube#video",
            "etag": "x7ubnFkfB7Ank2bj6e2Zu9niwYM",
            "id": "_6Dq7pHgxZI",
            "snippet": {
                "publishedAt": "2022-01-16T15:31:41Z",
                "channelId": "UC02CcVtL7nw_XvkKWAyMIWQ",
                "title": "Hướng dẫn tham gia Airdrop + IDO Whitelist  GreenLand NFT Kèo XX Tài khoản",
                "description": "Hướng dẫn tham gia Airdrop + IDO Whitelist  GreenLand NFT Kèo XX Tài khoản.\n- IDO và Airdrop ngày 25/1 /2022 phân phối\nLink tham gia IDO: https://wn.nr/n9gyDH\nLink tham gia Airdrop: https://wn.nr/WPQUNb   \n\n-------------------------------------------------------------\n♨️TỔNG HƠP LINK SÀN GIAO DỊCH  LỚN CÁC BẠN CẦN PHẢI CÓ KHI THAM GIA MMO\n- Link sàn BINANCE:  https://accounts.binance.me/vi/register?ref=40359045\n- Link sàn Gate: https://www.gate.io/signup/2987699\n- Link sàn HOUBI : https://www.huobi.com/vi-vi/topic/invited/?invite_code=ij5q5\n- Link sàn OKEX:  https://www.okex.com/vi/join/1933407\n- Link sàn MXC : https://www.mxc.ai/auth/signup?invite...\n- Link sàn HOTBIT : https://www.hotbit.io/register?ref=642514\n- Link sàn KUCOIN: https://www.kucoin.com/ucenter/signup?rcode=2NJad1P\n-------------------------------------------------------------\n✅ Channel COSTV : https://cos.tv/channel/18945441871079424\n✅ Channel: https://t.me/chiaseonline2020\n✅ Group chat: https://t.me/chiaseonline\n👉Facebook group :  https://www.facebook.com/groups/424960875127610\n#kèo_airdrop_mới_nhất #keox10x50x100 #cách_swap_trên_ví_trust _airdrop_coin #Telegram #Twitter #Trust_wallet #Safepal #Metamask #Coin #Swap #Xổ_số  #token_xổ_số #pancakeswap  #Trade_coin #cointop #kèo_xổ_số #Airdrop_mới_nhất #bscan #Binance #smartchain #airdrop #Claim #kèo_Chatbot #MXC #Hotbit #Bitmart #VNDC #gate #Crypto #Hướng_dẫn_claim #Hướng_dẫn_swap #Mmo #Crypto #Doge #Token #Free #Đào_coin #coin_rác #Kiếm_tiền_online #Kiếm_tiền_trên_mạng #Kinh_doanh_online #Safemoon #BabyDoge #Nft #solana #uniswap #Đào_coin_free #Hold_coin_top #Top10Coin #Trade_coin_sàn_binance #tải_app_đào_coin #trx #Xrp #Solana #Hướng_dẫn_làm_airdrop #Shiba #Bitcoin #Remitano #NFT #Box #Gamefi #Metaverse #Meta #Raca #Saitama #Floki # Kèo Sổ Số",
                "thumbnails": {
                    "default": { "url": "https://i.ytimg.com/vi/_6Dq7pHgxZI/default.jpg", "width": 120, "height": 90 },
                    "medium": {
                        "url": "https://i.ytimg.com/vi/_6Dq7pHgxZI/mqdefault.jpg",
                        "width": 320,
                        "height": 180
                    },
                    "high": { "url": "https://i.ytimg.com/vi/_6Dq7pHgxZI/hqdefault.jpg", "width": 480, "height": 360 },
                    "standard": {
                        "url": "https://i.ytimg.com/vi/_6Dq7pHgxZI/sddefault.jpg",
                        "width": 640,
                        "height": 480
                    }
                },
                "channelTitle": "Chia Sẻ Online",
                "tags": [
                    "kiếm tiền online 2020",
                    "chia sẻ online",
                    "kiem tien free",
                    "kèo sổ số",
                    "claim token",
                    "x10 tài khoản",
                    "cliam coin",
                    "airdrop",
                    "kiếm tiền online",
                    "sàm giao dịch",
                    "top coin",
                    "nhận coin miễn phí",
                    "đào coin",
                    "kèo xổ số",
                    "kèo claim",
                    "kèo ngon",
                    "airdrop coin"
                ],
                "categoryId": "27",
                "liveBroadcastContent": "none",
                "defaultLanguage": "vi",
                "localized": {
                    "title": "Hướng dẫn tham gia Airdrop + IDO Whitelist  GreenLand NFT Kèo XX Tài khoản",
                    "description": "Hướng dẫn tham gia Airdrop + IDO Whitelist  GreenLand NFT Kèo XX Tài khoản.\n- IDO và Airdrop ngày 25/1 /2022 phân phối\nLink tham gia IDO: https://wn.nr/n9gyDH\nLink tham gia Airdrop: https://wn.nr/WPQUNb   \n\n-------------------------------------------------------------\n♨️TỔNG HƠP LINK SÀN GIAO DỊCH  LỚN CÁC BẠN CẦN PHẢI CÓ KHI THAM GIA MMO\n- Link sàn BINANCE:  https://accounts.binance.me/vi/register?ref=40359045\n- Link sàn Gate: https://www.gate.io/signup/2987699\n- Link sàn HOUBI : https://www.huobi.com/vi-vi/topic/invited/?invite_code=ij5q5\n- Link sàn OKEX:  https://www.okex.com/vi/join/1933407\n- Link sàn MXC : https://www.mxc.ai/auth/signup?invite...\n- Link sàn HOTBIT : https://www.hotbit.io/register?ref=642514\n- Link sàn KUCOIN: https://www.kucoin.com/ucenter/signup?rcode=2NJad1P\n-------------------------------------------------------------\n✅ Channel COSTV : https://cos.tv/channel/18945441871079424\n✅ Channel: https://t.me/chiaseonline2020\n✅ Group chat: https://t.me/chiaseonline\n👉Facebook group :  https://www.facebook.com/groups/424960875127610\n#kèo_airdrop_mới_nhất #keox10x50x100 #cách_swap_trên_ví_trust _airdrop_coin #Telegram #Twitter #Trust_wallet #Safepal #Metamask #Coin #Swap #Xổ_số  #token_xổ_số #pancakeswap  #Trade_coin #cointop #kèo_xổ_số #Airdrop_mới_nhất #bscan #Binance #smartchain #airdrop #Claim #kèo_Chatbot #MXC #Hotbit #Bitmart #VNDC #gate #Crypto #Hướng_dẫn_claim #Hướng_dẫn_swap #Mmo #Crypto #Doge #Token #Free #Đào_coin #coin_rác #Kiếm_tiền_online #Kiếm_tiền_trên_mạng #Kinh_doanh_online #Safemoon #BabyDoge #Nft #solana #uniswap #Đào_coin_free #Hold_coin_top #Top10Coin #Trade_coin_sàn_binance #tải_app_đào_coin #trx #Xrp #Solana #Hướng_dẫn_làm_airdrop #Shiba #Bitcoin #Remitano #NFT #Box #Gamefi #Metaverse #Meta #Raca #Saitama #Floki # Kèo Sổ Số"
                },
                "defaultAudioLanguage": "en-US"
            }
        }
    ],
    "pageInfo": { "totalResults": 1, "resultsPerPage": 1 }
}
